cdock/__init__.py
cdock/cli.py
cdock/manager.py
cdock/project.py
cdock/Dockerfile
cdock/entrypoint.sh
cdock-0.1.0.dist-info/METADATA
cdock-0.1.0.dist-info/WHEEL
cdock-0.1.0.dist-info/entry_points.txt
cdock-0.1.0.dist-info/RECORD
