Metadata-Version: 2.4
Name: cdock
Version: 0.1.0
Summary: Docker-based Claude Code runner with orchestration support
Author-email: fred monroe <fred@fredmonroe.com>
Requires-Python: >=3.13
Requires-Dist: click>=8.2.1
Requires-Dist: docker>=7.1.0
Requires-Dist: gitpython>=3.1.44
Requires-Dist: pydantic-settings>=2.10.1
Requires-Dist: pygithub>=2.6.1
Requires-Dist: pyyaml>=6.0.2
Requires-Dist: rich>=14.0.0
